yt_stats_wrangler/__init__.py
yt_stats_wrangler/config.py
yt_stats_wrangler-0.2.0.dist-info/licenses/LICENSE
yt_stats_wrangler-0.2.0.dist-info/METADATA
yt_stats_wrangler-0.2.0.dist-info/WHEEL
yt_stats_wrangler-0.2.0.dist-info/top_level.txt
yt_stats_wrangler-0.2.0.dist-info/RECORD
