Metadata-Version: 2.4
Name: yt_stats_wrangler
Version: 0.2.0
Summary: A Python package to collect and wrangle YouTube video and channel statistics using the YouTube Data API v3
Home-page: https://github.com/ChristianD37/yt-stats-wrangler
Author: Christian Duenas
Author-email: Christian Duenas <christianduenas1998@gmail.com>
License: MIT
Project-URL: Homepage, https://github.com/ChristianD37/yt-stats-wrangler
Keywords: youtube,api,youtube-data-api,statistics,analytics,youtube-v3
Classifier: Programming Language :: Python :: 3
Classifier: License :: OSI Approved :: MIT License
Classifier: Operating System :: OS Independent
Requires-Python: >=3.7
License-File: LICENSE
Requires-Dist: google-api-python-client
Requires-Dist: isodate
Provides-Extra: pandas
Requires-Dist: pandas; extra == "pandas"
Provides-Extra: polars
Requires-Dist: polars; extra == "polars"
Provides-Extra: pyspark
Requires-Dist: pyspark; extra == "pyspark"
Dynamic: author
Dynamic: home-page
Dynamic: license-file
Dynamic: requires-python
